pydfirram/__init__.py
pydfirram/core/__init__.py
pydfirram/core/base.py
pydfirram/core/handler.py
pydfirram/core/renderer.py
pydfirram/core/utils.py
pydfirram/modules/__init__.py
pydfirram/modules/windows.py
pydfirram/py.typed
pydfirram-2.0.0.dist-info/LICENSE
pydfirram-2.0.0.dist-info/METADATA
pydfirram-2.0.0.dist-info/WHEEL
pydfirram-2.0.0.dist-info/RECORD
