Metadata-Version: 2.1
Name: pydfirram
Version: 2.0.0
Summary: A Python library for memory forensics tasks.
License: AGPL-3.0
Author: Braguette
Author-email: alexis.debrito@ecole2600.com
Requires-Python: >=3.10,<4.0
Classifier: Development Status :: 2 - Pre-Alpha
Classifier: Intended Audience :: Developers
Classifier: License :: OSI Approved :: GNU Affero General Public License v3
Classifier: License :: OSI Approved :: MIT License
Classifier: Natural Language :: English
Classifier: Programming Language :: Python :: 3
Classifier: Programming Language :: Python :: 3.10
Classifier: Programming Language :: Python :: 3.11
Classifier: Programming Language :: Python :: 3.12
Provides-Extra: dev
Provides-Extra: doc
Provides-Extra: test
Requires-Dist: graphviz (>=0.20.3,<0.21.0)
Requires-Dist: jupyter (>=1.0.0,<2.0.0)
Requires-Dist: loguru (>=0.7.2,<0.8.0)
Requires-Dist: mike (>=1.1.2,<2.0.0) ; extra == "doc"
Requires-Dist: pandas (>=2.2.2,<3.0.0)
Requires-Dist: regex (>=2024.4.28,<2025.0.0)
Requires-Dist: volatility3 (>=2.5.2,<3.0.0)
